{
    "id": 1,

    "name": "lateral_raises_exercise",

    "poses": [
        1,
        2
    ],

    "rules": [
        {
        "pose_name": "arms_down",
        "feature": "LEFT_SHOULDER",
        "operator": ">",
        "value": 15.0,
        "message": "Опустите левую руку полностью"
        },
        {
        "pose_name": "arms_down",
        "feature": "RIGHT_SHOULDER",
        "operator": ">",
        "value": 15.0,
        "message": "Опустите правую руку полностью"
        },
        {
        "pose_name": "arms_down",
        "feature": "LEFT_ELBOW",
        "operator": "<",
        "value": 170.0,
        "message": "Держите левую руку прямой"
        },
        {
        "pose_name": "arms_down",
        "feature": "RIGHT_ELBOW",
        "operator": "<",
        "value": 170.0,
        "message": "Держите правую руку прямой"
        },
        {
        "pose_name": "arms_down",
        "feature": "LEFT_KNEE",
        "operator": "<",
        "value": 170.0,
        "message": "Выпрямите левую ногу"
        },
        {
        "pose_name": "arms_down",
        "feature": "RIGHT_KNEE",
        "operator": "<",
        "value": 170.0,
        "message": "Выпрямите правую ногу"
        },
        {
        "pose_name": "t_pose",
        "feature": "LEFT_SHOULDER",
        "operator": "<",
        "value": 75.0,
        "message": "Поднимите левую руку выше"
        },
        {
        "pose_name": "t_pose",
        "feature": "RIGHT_SHOULDER",
        "operator": "<",
        "value": 75.0,
        "message": "Поднимите правую руку выше"
        },
        {
        "pose_name": "t_pose",
        "feature": "LEFT_ELBOW",
        "operator": "<",
        "value": 160.0,
        "message": "Не сгибайте левый локоть при подъёме"
        },
        {
        "pose_name": "t_pose",
        "feature": "RIGHT_ELBOW",
        "operator": "<",
        "value": 160.0,
        "message": "Не сгибайте правый локоть при подъёме"
        },
        {
        "pose_name": "t_pose",
        "feature": "LEFT_KNEE",
        "operator": "<",
        "value": 170.0,
        "message": "Не приседайте, держите ноги прямыми"
        },
        {
        "pose_name": "t_pose",
        "feature": "RIGHT_KNEE",
        "operator": "<",
        "value": 170.0,
        "message": "Не приседайте, держите ноги прямыми"
        }
    ]
}